MANIFEST.in
setup.py
lib/liji.c
lib/liji.h
liji/__init__.py
liji/benchmark.py
liji.egg-info/PKG-INFO
liji.egg-info/SOURCES.txt
liji.egg-info/dependency_links.txt
liji.egg-info/top_level.txt
liji/ext/__init__.py
liji/ext/_liji.c