Metadata-Version: 1.1
Name: liji
Version: 0.1.1
Summary: liji
Home-page: UNKNOWN
Author: globo.com
Author-email: cezarsa@gmail.com
License: MIT
Keywords: json
Platform: UNKNOWN
Classifier: Development Status :: 4 - Beta
Classifier: Intended Audience :: Developers
Classifier: License :: OSI Approved :: MIT License
Classifier: Natural Language :: English
Classifier: Operating System :: MacOS
Classifier: Operating System :: POSIX :: Linux
Classifier: Programming Language :: Python :: 2.7
